LICENSE
MANIFEST.in
README.rst
buildout.cfg
develop.cfg
requirements.txt
setup.py
version.txt
bob/__init__.py
bob.db.hci_tagging.egg-info/PKG-INFO
bob.db.hci_tagging.egg-info/SOURCES.txt
bob.db.hci_tagging.egg-info/dependency_links.txt
bob.db.hci_tagging.egg-info/entry_points.txt
bob.db.hci_tagging.egg-info/not-zip-safe
bob.db.hci_tagging.egg-info/requires.txt
bob.db.hci_tagging.egg-info/top_level.txt
bob/db/__init__.py
bob/db/hci_tagging/__init__.py
bob/db/hci_tagging/create.py
bob/db/hci_tagging/driver.py
bob/db/hci_tagging/files.txt
bob/db/hci_tagging/metadata.csv
bob/db/hci_tagging/models.py
bob/db/hci_tagging/test.py
bob/db/hci_tagging/utils.py