Metadata-Version: 1.1
Name: bob.db.hci-tagging
Version: 1.1.0
Summary: Mahnob HCI-Tagging Database Access API for Bob
Home-page: https://gitlab.idiap.ch/bob/bob.db.cohface
Author: Andre Anjos
Author-email: andre.anjos@idiap.ch
License: BSD
Keywords: bob,database,manhob,hci-tagging
Platform: UNKNOWN
Classifier: Framework :: Bob
Classifier: Natural Language :: English
Classifier: Programming Language :: Python
Classifier: Programming Language :: Python :: 3
Classifier: Development Status :: 4 - Beta
Classifier: Intended Audience :: Developers
Classifier: License :: OSI Approved :: BSD License
Classifier: Topic :: Software Development :: Libraries :: Python Modules
